image.py
cs20_image-1.5.5.dist-info/DESCRIPTION.rst
cs20_image-1.5.5.dist-info/METADATA
cs20_image-1.5.5.dist-info/RECORD
cs20_image-1.5.5.dist-info/WHEEL
cs20_image-1.5.5.dist-info/metadata.json
cs20_image-1.5.5.dist-info/top_level.txt
