Metadata-Version: 2.0
Name: cs20-image
Version: 1.5.5
Summary: Image manipulation library for media computation education
Home-page: https://github.com/schellenberg/cImage
Author: Brad Miller and Dan Schellenberg
Author-email: schellenberg@gmail.com
License: GPL
Keywords: image,education
Platform: UNKNOWN
Classifier: Development Status :: 5 - Production/Stable
Classifier: Environment :: Console
Classifier: Intended Audience :: Education
Classifier: License :: OSI Approved :: GNU General Public License v3 or later (GPLv3+)
Classifier: Operating System :: MacOS
Classifier: Operating System :: Unix
Classifier: Programming Language :: Python
Classifier: Programming Language :: Python :: 3.4
Classifier: Topic :: Education
Requires-Dist: Pillow (>=2.9.0)
